tfsurgeon/__init__.py
tfsurgeon/tfsurgeon.py
tfsurgeon/utils/__init__.py
tfsurgeon/utils/lambda_layers.py
tfsurgeon/utils/reader.py
tfsurgeon/utils/remove_by_names.py
tfsurgeon/utils/remove_type_editor.py
tfsurgeon/utils/replace_by_counter.py
tfsurgeon/utils/replace_type_editor.py
tfsurgeon-0.0.8.dist-info/LICENSE
tfsurgeon-0.0.8.dist-info/METADATA
tfsurgeon-0.0.8.dist-info/WHEEL
tfsurgeon-0.0.8.dist-info/top_level.txt
tfsurgeon-0.0.8.dist-info/RECORD
