Metadata-Version: 2.1
Name: tfsurgeon
Version: 0.0.8
Summary: Edits tensorflow model layers
Author-email: Edouard Yvinec <ey@datakalab.com>
Classifier: Programming Language :: Python :: 3
Requires-Python: >=3.9
License-File: LICENSE
